Workbook

Sheet 原始数据
A1: 投资配置数据
A2: 金额单位：万元；已计入本周操作8笔买入，共10.4万元；占比＝数值÷合计。
A4: 原图大类 | B4: 投资品种 | C4: 数值（万元） | D4: 制图大类 | E4: 占已填合计 | F4: 说明 | G4: 色号 | I4: 制图大类 | J4: 合计 | K4: 占比 | L4: 饼图标签 | M4: 饼图数值
A5: 科技 | B5: 海力士 | C5: 10.4 | D5: 科技 | E5: =C5/$C$23 -> 0.13248408 | F5: 已计入本周买入：0.8；买入海力士波段 | G5: #2563EB | I5: 科技 | J5: =SUMIF(D5:D22,I5,C5:C22) -> 24.5 | K5: =J5/$C$23 -> 0.31210191 | L5: =I5&" "&TEXT(K5,"0.00%")&CHAR(10)&B5&" "&TEXT(E5,"0.00%")&CHAR(10)&B6&" "&TEXT(E6,"0.00%")&CHAR(10)&B7&" "&TEXT(E7,"0.00%")&CHAR(10)&B8&" "&TEXT(E8,"0.00%")&CHAR(10)&B9&" "&TEXT(E9,"0.00%") -> 科技 31.21% 海力士 13.25% 台积电 1.66% 港股中芯国际 7.13% 科创50ETF 8.28% 特斯拉 0.89% | M5: =J5 -> 24.5
A6: 科技 | B6: 台积电 | C6: 1.3 | D6: 科技 | E6: =C6/$C$23 -> 0.01656051 | F6: 已计入本周买入：0.3；买入台积电 | G6: #2563EB | I6: 有色 | J6: =SUMIF(D5:D22,I6,C5:C22) -> 30.6 | K6: =J6/$C$23 -> 0.38980892 | L6: =I6&" "&TEXT(K6,"0.00%")&CHAR(10)&B10&" "&TEXT(E10,"0.00%")&CHAR(10)&B11&" "&TEXT(E11,"0.00%")&CHAR(10)&B12&" "&TEXT(E12,"0.00%")&CHAR(10)&B13&" "&TEXT(E13,"0.00%") -> 有色 38.98% 山金国际 17.20% 中矿资源 10.83% 紫金矿业 8.41% 中国铝业 2.55% | M6: =J6 -> 30.6
A7: 科技 | B7: 港股中芯国际 | C7: 5.6 | D7: 科技 | E7: =C7/$C$23 -> 0.07133758 | F7: 已计入本周买入：5.6；买入港股中芯国际 | G7: #2563EB | I7: 锂矿 | J7: =SUMIF(D5:D22,I7,C5:C22) -> 2.4 | K7: =J7/$C$23 -> 0.030573248 | L7: =I7&" "&TEXT(K7,"0.00%")&CHAR(10)&B14&" "&TEXT(E14,"0.00%")&CHAR(10)&B15&" "&TEXT(E15,"0.00%")&CHAR(10)&B16&" "&TEXT(E16,"0.00%")&CHAR(10)&B17&" "&TEXT(E17,"0.00%") -> 锂矿 3.06% 赣锋 0.51% 天齐 0.51% 融捷股份 0.76% 港股赣锋 1.27% | M7: =J7 -> 2.4
A8: 科技 | B8: 科创50ETF | C8: 6.5 | D8: 科技 | E8: =C8/$C$23 -> 0.082802548 | G8: #2563EB | I8: 周期股 | J8: =SUMIF(D5:D22,I8,C5:C22) -> 0.4 | K8: =J8/$C$23 -> 0.0050955414 | L8: =I8&" "&TEXT(K8,"0.00%")&CHAR(10)&B18&" "&TEXT(E18,"0.00%") -> 周期股 0.51% 大金重工 0.51% | M8: =J8 -> 0.4
A9: 科技 | B9: 特斯拉 | C9: 0.7 | D9: 科技 | E9: =C9/$C$23 -> 0.0089171975 | F9: 已计入本周买入：0.7 | G9: #2563EB | I9: 医药 | J9: =SUMIF(D5:D22,I9,C5:C22) -> 1.6 | K9: =J9/$C$23 -> 0.020382166 | L9: =I9&" "&TEXT(K9,"0.00%")&CHAR(10)&B19&" "&TEXT(E19,"0.00%")&CHAR(10)&B20&" "&TEXT(E20,"0.00%") -> 医药 2.04% 港股创新药ETF 0.76% 广发创新药ETF 1.27% | M9: =J9 -> 1.6
A10: 有色 | B10: 山金国际 | C10: 13.5 | D10: 有色 | E10: =C10/$C$23 -> 0.17197452 | G10: #D97706 | I10: 红利 | J10: =SUMIF(D5:D22,I10,C5:C22) -> 1 | K10: =J10/$C$23 -> 0.012738854 | L10: =I10&" "&TEXT(K10,"0.00%")&CHAR(10)&B21&" "&TEXT(E21,"0.00%") -> 红利 1.27% A500 广发ETF 1.27% | M10: =J10 -> 1
A11: 有色 | B11: 中矿资源 | C11: 8.5 | D11: 有色 | E11: =C11/$C$23 -> 0.10828025 | G11: #D97706 | I11: 现金 | J11: =SUMIF(D5:D22,I11,C5:C22) -> 18 | K11: =J11/$C$23 -> 0.22929936 | L11: =I11&" "&TEXT(K11,"0.00%") -> 现金 22.93% | M11: =J11 -> 18
A12: 有色 | B12: 紫金矿业 | C12: 6.6 | D12: 有色 | E12: =C12/$C$23 -> 0.084076433 | G12: #D97706 | I12: 图表品种标签 | J12: 制图数值
A13: 有色 | B13: 中国铝业 | C13: 2 | D13: 有色 | E13: =C13/$C$23 -> 0.025477707 | G13: #D97706 | I13: =B5 -> 海力士 | J13: =C5 -> 10.4
A14: 锂矿 | B14: 赣锋 | C14: 0.4 | D14: 锂矿 | E14: =C14/$C$23 -> 0.0050955414 | G14: #059669 | I14: =B6 -> 台积电 | J14: =C6 -> 1.3
A15: 锂矿 | B15: 天齐 | C15: 0.4 | D15: 锂矿 | E15: =C15/$C$23 -> 0.0050955414 | G15: #059669 | I15: =B7 -> 港股中芯国际 | J15: =C7 -> 5.6
A16: 锂矿 | B16: 融捷股份 | C16: 0.6 | D16: 锂矿 | E16: =C16/$C$23 -> 0.0076433121 | G16: #059669 | I16: =B8 -> 科创50ETF | J16: =C8 -> 6.5
A17: 锂矿 | B17: 港股赣锋 | C17: 1 | D17: 锂矿 | E17: =C17/$C$23 -> 0.012738854 | F17: 按用户确认归入锂矿 | G17: #059669 | I17: =B9 -> 特斯拉 | J17: =C9 -> 0.7
A18: 周期股 | B18: 大金重工 | C18: 0.4 | D18: 周期股 | E18: =C18/$C$23 -> 0.0050955414 | F18: 已计入本周买入：0.4 | G18: #9333EA | I18: =B10 -> 山金国际 | J18: =C10 -> 13.5
A19: 医药 | B19: 港股创新药ETF | C19: 0.6 | D19: 医药 | E19: =C19/$C$23 -> 0.0076433121 | F19: 已计入本周买入：0.6 | G19: #DC2626 | I19: =B11 -> 中矿资源 | J19: =C11 -> 8.5
A20: 医药 | B20: 广发创新药ETF | C20: 1 | D20: 医药 | E20: =C20/$C$23 -> 0.012738854 | F20: 已计入本周买入：1 | G20: #DC2626 | I20: =B12 -> 紫金矿业 | J20: =C12 -> 6.6
A21: 红利 | B21: A500 广发ETF | C21: 1 | D21: 红利 | E21: =C21/$C$23 -> 0.012738854 | F21: 已计入本周买入：1 | G21: #0891B2 | I21: =B13 -> 中国铝业 | J21: =C13 -> 2
A22: 现金 | B22: 现金 | C22: 18 | D22: 现金 | E22: =C22/$C$23 -> 0.22929936 | F22: 已扣除本周买入合计10.4 | G22: #64748B | I22: =B14 -> 赣锋 | J22: =C14 -> 0.4
A23: 已填写合计 | C23: =SUM(C5:C22) -> 78.5 | E23: =SUM(E5:E22) -> 1 | I23: =B15 -> 天齐 | J23: =C15 -> 0.4
I24: =B16 -> 融捷股份 | J24: =C16 -> 0.6
A25: 分类按本周操作填写：新增周期股、医药、红利；A500 广发ETF按用户分类归入红利。 | I25: =B17 -> 港股赣锋 | J25: =C17 -> 1
A26: 海力士波段并入海力士；原中芯国际零持仓项改为港股中芯国际。 | I26: =B18 -> 大金重工 | J26: =C18 -> 0.4
A27: 本周买入已计入，勿重复添加；现金扣减10.4万元，配置合计仍为78.5万元。 | I27: =B19 -> 港股创新药ETF | J27: =C19 -> 0.6
I28: =B20 -> 广发创新药ETF | J28: =C20 -> 1
I29: =B21 -> A500 广发ETF | J29: =C21 -> 1
I30: =B22 -> 现金 | J30: =C22 -> 18

Sheet 饼形图
A1: 投资配置占比
A2: 七大类分色，包含本周买入；各标的占比均按配置总额计算。
A3: ="按所列数值合计"&TEXT(原始数据!C23,"0.0#")&"万元计算；已计入本周买入10.4万元。" -> 按所列数值合计78.5万元计算；已计入本周买入10.4万元。
L5: 大类 | M5: 投资品种 | N5: 数值（万元） | O5: 占比
L6: =原始数据!D5 -> 科技 | M6: =原始数据!B5 -> 海力士 | N6: =原始数据!C5 -> 10.4 | O6: =原始数据!E5 -> 0.13248408
L7: =原始数据!D6 -> 科技 | M7: =原始数据!B6 -> 台积电 | N7: =原始数据!C6 -> 1.3 | O7: =原始数据!E6 -> 0.01656051
L8: =原始数据!D7 -> 科技 | M8: =原始数据!B7 -> 港股中芯国际 | N8: =原始数据!C7 -> 5.6 | O8: =原始数据!E7 -> 0.07133758
L9: =原始数据!D8 -> 科技 | M9: =原始数据!B8 -> 科创50ETF | N9: =原始数据!C8 -> 6.5 | O9: =原始数据!E8 -> 0.082802548
L10: =原始数据!D9 -> 科技 | M10: =原始数据!B9 -> 特斯拉 | N10: =原始数据!C9 -> 0.7 | O10: =原始数据!E9 -> 0.0089171975
L11: =原始数据!D10 -> 有色 | M11: =原始数据!B10 -> 山金国际 | N11: =原始数据!C10 -> 13.5 | O11: =原始数据!E10 -> 0.17197452
L12: =原始数据!D11 -> 有色 | M12: =原始数据!B11 -> 中矿资源 | N12: =原始数据!C11 -> 8.5 | O12: =原始数据!E11 -> 0.10828025
L13: =原始数据!D12 -> 有色 | M13: =原始数据!B12 -> 紫金矿业 | N13: =原始数据!C12 -> 6.6 | O13: =原始数据!E12 -> 0.084076433
L14: =原始数据!D13 -> 有色 | M14: =原始数据!B13 -> 中国铝业 | N14: =原始数据!C13 -> 2 | O14: =原始数据!E13 -> 0.025477707
L15: =原始数据!D14 -> 锂矿 | M15: =原始数据!B14 -> 赣锋 | N15: =原始数据!C14 -> 0.4 | O15: =原始数据!E14 -> 0.0050955414
L16: =原始数据!D15 -> 锂矿 | M16: =原始数据!B15 -> 天齐 | N16: =原始数据!C15 -> 0.4 | O16: =原始数据!E15 -> 0.0050955414
L17: =原始数据!D16 -> 锂矿 | M17: =原始数据!B16 -> 融捷股份 | N17: =原始数据!C16 -> 0.6 | O17: =原始数据!E16 -> 0.0076433121
... L23: =原始数据!D22 -> 现金 | M23: =原始数据!B22 -> 现金 | N23: =原始数据!C22 -> 18 | O23: =原始数据!E22 -> 0.22929936
L26: 大类汇总 | M26: 数值（万元） | N26: 占比
L27: =原始数据!I5 -> 科技 | M27: =原始数据!J5 -> 24.5 | N27: =原始数据!K5 -> 0.31210191
L28: =原始数据!I6 -> 有色 | M28: =原始数据!J6 -> 30.6 | N28: =原始数据!K6 -> 0.38980892
L29: =原始数据!I7 -> 锂矿 | M29: =原始数据!J7 -> 2.4 | N29: =原始数据!K7 -> 0.030573248
L30: =原始数据!I8 -> 周期股 | M30: =原始数据!J8 -> 0.4 | N30: =原始数据!K8 -> 0.0050955414
L31: =原始数据!I9 -> 医药 | M31: =原始数据!J9 -> 1.6 | N31: =原始数据!K9 -> 0.020382166
L32: =原始数据!I10 -> 红利 | M32: =原始数据!J10 -> 1 | N32: =原始数据!K10 -> 0.012738854
L33: =原始数据!I11 -> 现金 | M33: =原始数据!J11 -> 18 | N33: =原始数据!K11 -> 0.22929936
A35: 新增类别已纳入饼图；所有比例按原始数据计算，未放大较小扇区。

Sheet 本周操作
A1: 日期 | B1: 类别 | C1: 操作 | D1: 现金变化
B2: 周期股 | C2: 买入大金重工100股 | D2: -0.4
B3: 医药 | C3: 买入港股创新药ETF | D3: -0.6
B4: 医药 | C4: 买入广发创新药ETF | D4: -1
B5: 科技 | C5: 买入特斯拉 | D5: -0.7
B6: 科技 | C6: 买入台积电 | D6: -0.3
B7: 科技 | C7: 买入海力士波段 | D7: -0.8
B8: 科技 | C8: 买入港股中芯国际 | D8: -5.6
B9: 红利 | C9: 买入A500 广发ETF | D9: -1
A10: 9月30号 | D10: =SUM(D2:D9) -> -10.4

Sheet 后续操作计划
A1: 日期 | B1: 操作 | C1: 现金变化
B3: 海力士卖出波段 | C3: 9月30号持仓海力士10.4, 后续涨到目标位，卖出波段操作
A4: 10月7号附近，海力士解禁 | B4: 如果暴跌，买入一部分

Sheet 投资原则
A1: 一定要高赔率，少搞几次，但每次都要非常赚才行。在质量不在数量，否则做的越多，错的可能性越多
A2: 高确定性标的，必须成本低，才能挣到时间复利的钱，否则你根本享受不到
A3: 科技为主线，锂矿股博取超额收益，拒绝变成彻彻底底的赌狗，单压一只，把自己搞死
A4: 买之前就知道大概可以涨到多少，有大概多少的收益，而不是想着两三个月内可以翻倍的可能性
A5: 挣了钱，就要享受，让自己放松下来最重要，不要继续瞎折腾了，心理安稳，精神放松才行
A6: 远离还债模式，你会被消耗，透支的

Sheet 买卖原则
A1: 买入原则 | B1: 止损原则
A2: 远期估值，高赔率 | B2: 1 放量大阴线
A3: 近期涨幅，下跌买入 | B3: 2跌破20日均线
A4: 均线原则，20日均线，20周均线
A5: 分批买入原则（50），后手原则（30），极端突发原则（20）
A6: 总体仓位，7成基本仓，3分机动仓位，绝不满仓，绝不梭哈

Sheet 追踪标的
A1: spacx
A2: 宁德时代

Sheet 情绪影响
A1: 杜绝慌慌张张，急急忙忙，非买不可的强迫症，否则一定会出错，百分百出错
A2: 放弃一把暴富的幻想，总用可以挣几倍来安稳自己眼前不断加重的损失，还有可以回本的机会，结果就是越亏越严重，把所有希望寄希望与一次小概率翻盘上，心理压力越来越大，动作越来越变形
A3: 找到让自己心安，可以彻底放松的事物，比如音乐，固定工资，不要那么应激了，总觉得必须用尽全力，没有任何负债了才能彻底享受。你还是太缺乏安全感，太极端了
